alpha1p/__init__.py
alpha1p/version.py
alpha1p/.ipynb_checkpoints/__init__-checkpoint.py
alpha1p/.ipynb_checkpoints/version-checkpoint.py
alpha1p/Datas/all_actions.csv
alpha1p/Datas/resample_filter/kaiser_best.npz
alpha1p/Datas/resample_filter/kaiser_fast.npz
alpha1p/dance/__init__.py
alpha1p/dance/conversion.py
alpha1p/dance/process.py
alpha1p/dance/similarity.py
alpha1p/dance/.ipynb_checkpoints/__init__-checkpoint.py
alpha1p/dance/.ipynb_checkpoints/conversion-checkpoint.py
alpha1p/dance/.ipynb_checkpoints/process-checkpoint.py
alpha1p/dance/.ipynb_checkpoints/similarity-checkpoint.py
alpha1p/robot/__init__.py
alpha1p/robot/bthandler.py
alpha1p/robot/control.py
alpha1p/robot/robot.py
alpha1p/robot/.ipynb_checkpoints/__init__-checkpoint.py
alpha1p/robot/.ipynb_checkpoints/bthandler-checkpoint.py
alpha1p/robot/.ipynb_checkpoints/control-checkpoint.py
alpha1p/robot/.ipynb_checkpoints/robot-checkpoint.py
alpha1p-0.1.5.dist-info/LICENSE
alpha1p-0.1.5.dist-info/METADATA
alpha1p-0.1.5.dist-info/WHEEL
alpha1p-0.1.5.dist-info/top_level.txt
alpha1p-0.1.5.dist-info/RECORD
